Core/Constants.py
Core/EvaluateModel.py
Core/FeatureExtraction.py
Core/FeatureSelection.py
Core/Model.py
Core/PreProcessing.py
Core/__init__.py
Regression/DecisionTreeRegression.py
Regression/OrdinaryLeastSquare.py
Regression/RandomForestRegression.py
Regression/SupportVectorRegression.py
Regression/__init__.py
model_selection-0.0.1.dist-info/METADATA
model_selection-0.0.1.dist-info/WHEEL
model_selection-0.0.1.dist-info/top_level.txt
model_selection-0.0.1.dist-info/RECORD
