Metadata-Version: 2.1
Name: model_selection
Version: 0.0.1
Summary: A Library which provides more information about suitable Machine learning algorithm for your dataset
Home-page: https://github.com/ManikandanJeyabal/ChooseMyALGO
Author: Manikandan Jeyabal
Author-email: ManikandanJeyabal029@gmail.com
License: UNKNOWN
Platform: UNKNOWN
Classifier: Programming Language :: Python :: 3
Classifier: License :: OSI Approved :: MIT License
Classifier: Operating System :: OS Independent
Requires-Python: >=3.7
